[[{"f": 1269}, {"f": 1269}, {"f": 1269}, {"f": 1269}, {"f": 1269}, {"f": 1269}, {"f": 1269}, {"f": 1269}, {"f": 1269}, {"f": 1269}, {"f": 1269}, {"f": 1269}, {"f": 1269}, {"f": 1269}, {"f": 1269}, {"f": 1269}, {"f": 1269}, {"f": 1269}, {"f": 1269}, {"f": 1269}, {"f": 1269}, {"f": 1269}, {"f": 1269}, {"f": 1269}, {"f": 1269}, {"f": 1269}, {"f": 1269}, {"f": 1269}, {"f": 1269}, {"f": 1269}, {"f": 1269}, {"f": 1269}, {"f": 1269}, {"f": 1269}, {"f": 1269}, {"f": 1269}, {"f": 1269}, {"f": 1269}, {"f": 1269}, {"f": 1269}, {"f": 1269}, {"f": 1269}, {"f": 1269}, {"f": 1269}, {"f": 1269}, {"f": 1269}, {"f": 1269}, {"f": 1269}, {"f": 1269}, {"f": 1269}, {"f": 1269}, {"f": 1269}, {"f": 1269}, {"f": 1269}, {"f": 1269}, {"f": 1269}, {"f": 1269}, {"f": 1269}, {"f": 1269}, {"f": 1269}, {"f": 1269}, {"f": 1269}, {"f": 1269}, {"f": 1269}], [{"f": 1269}, {"f": 1269}, {"f": 1269}, {"f": 1269}, {"f": 1269}, {"f": 1269}, {"f": 1269}, {"f": 1269}, {"f": 1269}, {"f": 1269}, {"f": 1269}, {"f": 1269}, {"f": 1269}, {"f": 1269}, {"f": 1269}, {"f": 1269}, {"f": 1269}, {"f": 1269}, {"f": 1269}, {"f": 1269}, {"f": 1269}, {"f": 1269}, {"f": 1269}, {"f": 1269}, {"f": 1269}, {"f": 1269}, {"f": 1269}, {"f": 1269}, {"f": 1269}, {"f": 1269}, {"f": 1269}, {"f": 1269}, {"f": 1269}, {"f": 1269}, {"f": 1269}, {"f": 1269}, {"f": 1269}, {"f": 1269}, {"f": 1269}, {"f": 1269}, {"f": 1269}, {"f": 1269}, {"f": 1269}, {"f": 1269}, {"f": 1269}, {"f": 1269}, {"f": 1269}, {"f": 1269}, {"f": 1269}, {"f": 1269}, {"f": 1269}, {"f": 1269}, {"f": 1269}, {"f": 1269}, {"f": 1269}, {"f": 1269}, {"f": 1269}, {"f": 1269}, {"f": 1269}, {"f": 1269}, {"f": 1269}, {"f": 1269}, {"f": 1269}, {"f": 1269}], [{"f": 1269}, {"f": 1269}, {"f": 1269}, {"f": 1269}, {"f": 1269}, {"f": 1269}, {"f": 1269}, {"f": 1269}, {"f": 1269}, {"f": 1269}, {"f": 1269}, {"f": 1269}, {"f": 1269}, {"f": 1269}, {"f": 1269}, {"f": 1269}, {"f": 1269}, {"f": 1269}, {"f": 1269}, {"f": 1269}, {"f": 1269}, {"f": 1269}, {"f": 1269}, {"f": 1269}, {"f": 1269}, {"f": 1269}, {"f": 1269}, {"f": 1269}, {"f": 1269}, {"f": 1269}, {"f": 1269}, {"f": 1269}, {"f": 1269}, {"f": 1269}, {"f": 1269}, {"f": 1269}, {"f": 1269}, {"f": 1269}, {"f": 1269}, {"f": 1269}, {"f": 1269}, {"f": 1269}, {"f": 1269}, {"f": 1269}, {"f": 1269}, {"f": 1269}, {"f": 1269}, {"f": 1269}, {"f": 1269}, {"f": 1269}, {"f": 1269}, {"f": 1269}, {"f": 1269}, {"f": 1269}, {"f": 1269}, {"f": 1269}, {"f": 1269}, {"f": 1269}, {"f": 1269}, {"f": 1269}, {"f": 1269}, {"f": 1269}, {"f": 1269}, {"f": 1269}], [{"f": 1269}, {"f": 1269}, {"f": 1269}, {"f": 1269}, {"f": 1269}, {"f": 1269}, {"f": 1269}, {"f": 1269}, {"f": 1269}, {"f": 1269}, {"f": 1269}, {"f": 1269}, {"f": 1269}, {"f": 1269}, {"f": 1269}, {"f": 1269}, {"f": 1269}, {"f": 1269}, {"f": 1269}, {"f": 1269}, {"f": 1269}, {"f": 1269}, {"f": 1269}, {"f": 1269}, {"f": 1269}, {"f": 1269}, {"f": 1269}, {"f": 1269}, {"f": 1269}, {"f": 1269}, {"f": 1269}, {"f": 1269}, {"f": 1269}, {"f": 1269}, {"f": 1269}, {"f": 1269}, {"f": 1269}, {"f": 1269}, {"f": 1269}, {"f": 1269}, {"f": 1269}, {"f": 1269}, {"f": 1269}, {"f": 1269}, {"f": 1269}, {"f": 1269}, {"f": 1269}, {"f": 1269}, {"f": 1269}, {"f": 1269}, {"f": 1269}, {"f": 1269}, {"f": 1269}, {"f": 1269}, {"f": 1269}, {"f": 1269}, {"f": 1269}, {"f": 1269}, {"f": 1269}, {"f": 1269}, {"f": 1269}, {"f": 1269}, {"f": 1269}, {"f": 1269}], [{"f": 1269}, {"f": 1269}, {"f": 1269}, {"f": 1269}, {"f": 1269}, {"f": 1269}, {"f": 1269}, {"f": 1269}, {"f": 1269}, {"f": 1269}, {"f": 1269}, {"f": 1269}, {"f": 1269}, {"f": 1269}, {"f": 1269}, {"f": 1269}, {"f": 1269}, {"f": 1269}, {"f": 1269}, {"f": 1269}, {"f": 1269}, {"f": 1269}, {"f": 1269}, {"f": 1269}, {"f": 1269}, {"f": 1269}, {"f": 1269}, {"f": 1269}, {"f": 1269}, {"f": 1269}, {"f": 1269}, {"f": 1269}, {"f": 1269}, {"f": 1269}, {"f": 1269}, {"f": 1269}, {"f": 1269}, {"f": 1269}, {"f": 1269}, {"f": 1269}, {"f": 1269}, {"f": 1269}, {"f": 1269}, {"f": 1269}, {"f": 1269}, {"f": 1269}, {"f": 1269}, {"f": 1269}, {"f": 1269}, {"f": 1269}, {"f": 1269}, {"f": 1269}, {"f": 1269}, {"f": 1269}, {"f": 1269}, {"f": 1269}, {"f": 1269}, {"f": 1269}, {"f": 1269}, {"f": 1269}, {"f": 1269}, {"f": 1269}, {"f": 1269}, {"f": 1269}], [{"f": 1269}, {"f": 1269}, {"f": 1269}, {"f": 1269}, {"f": 1269}, {"f": 1269}, {"f": 1269}, {"f": 1269}, {"f": 1269}, {"f": 1269}, {"f": 1269}, {"f": 1269}, {"f": 1269}, {"f": 1269}, {"f": 1269}, {"f": 1269}, {"f": 1269}, {"f": 1269}, {"f": 1269}, {"f": 1269}, {"f": 1269}, {"f": 1269}, {"f": 1269}, {"f": 1269}, {"f": 1269}, {"f": 1269}, {"f": 1269}, {"f": 1269}, {"f": 1269}, {"f": 1269}, {"f": 1269}, {"f": 1269}, {"f": 1269}, {"f": 1269}, {"f": 1269}, {"f": 1269}, {"f": 1269}, {"f": 1269}, {"f": 1269}, {"f": 1269}, {"f": 1269}, {"f": 1269}, {"f": 1269}, {"f": 1269}, {"f": 1269}, {"f": 1269}, {"f": 1269}, {"f": 1269}, {"f": 1269}, {"f": 1269}, {"f": 1269}, {"f": 1269}, {"f": 1269}, {"f": 1269}, {"f": 1269}, {"f": 1269}, {"f": 1269}, {"f": 1269}, {"f": 1269}, {"f": 1269}, {"f": 1269}, {"f": 1269}, {"f": 1269}, {"f": 1269}], [{"f": 1269}, {"f": 1269}, {"f": 1269}, {"f": 1269}, {"f": 1269}, {"f": 1269}, {"f": 1269}, {"f": 1269}, {"f": 1269}, {"f": 1269}, {"f": 1269}, {"f": 1269}, {"f": 1269}, {"f": 1269}, {"f": 1269}, {"f": 1269}, {"f": 1269}, {"f": 1269}, {"f": 1269}, {"f": 1269}, {"f": 1269}, {"f": 1269}, {"f": 1269}, {"f": 1269}, {"f": 1269}, {"f": 1269}, {"f": 1269}, {"f": 1269}, {"f": 1269}, {"f": 1269}, {"f": 1269}, {"f": 1269}, {"f": 1269}, {"f": 1269}, {"f": 1269}, {"f": 1269}, {"f": 1269}, {"f": 1269}, {"f": 1269}, {"f": 1269}, {"f": 1269}, {"f": 1269}, {"f": 1269}, {"f": 1269}, {"f": 1269}, {"f": 1269}, {"f": 1269}, {"f": 1269}, {"f": 1269}, {"f": 1269}, {"f": 1269}, {"f": 1269}, {"f": 1269}, {"f": 1269}, {"f": 1269}, {"f": 1269}, {"f": 1269}, {"f": 1269}, {"f": 1269}, {"f": 1269}, {"f": 1269}, {"f": 1269}, {"f": 1269}, {"f": 1269}], [{"f": 1269}, {"f": 1269}, {"f": 1269}, {"f": 1269}, {"f": 1269}, {"f": 1269}, {"f": 1269}, {"f": 1269}, {"f": 1269}, {"f": 1269}, {"f": 1269}, {"f": 1269}, {"f": 1269}, {"f": 1269}, {"f": 1269}, {"f": 1269}, {"f": 1269}, {"f": 1269}, {"f": 1269}, {"f": 1269}, {"f": 1269}, {"f": 1269}, {"f": 1269}, {"f": 1269}, {"f": 1269}, {"f": 1269}, {"f": 1269}, {"f": 1269}, {"f": 1269}, {"f": 1269}, {"f": 1269}, {"f": 1269}, {"f": 1269}, {"f": 1269}, {"f": 1269}, {"f": 1269}, {"f": 1269}, {"f": 1269}, {"f": 1269}, {"f": 1269}, {"f": 1269}, {"f": 1269}, {"f": 1269}, {"f": 1269}, {"f": 1269}, {"f": 1269}, {"f": 1269}, {"f": 1269}, {"f": 1269}, {"f": 1269}, {"f": 1269}, {"f": 1269}, {"f": 1269}, {"f": 1269}, {"f": 1269}, {"f": 1269}, {"f": 1269}, {"f": 1269}, {"f": 1269}, {"f": 1269}, {"f": 1269}, {"f": 1269}, {"f": 1269}, {"f": 1269}], [{"f": 1269}, {"f": 1269}, {"f": 1269}, {"f": 1269}, {"f": 1269}, {"f": 1269}, {"f": 1269}, {"f": 1269}, {"f": 1269}, {"f": 1269}, {"f": 1269}, {"f": 1269}, {"f": 1269}, {"f": 1269}, {"f": 1269}, {"f": 1269}, {"f": 1269}, {"f": 1269}, {"f": 1269}, {"f": 1269}, {"f": 1269}, {"f": 1269}, {"f": 1269}, {"f": 1269}, {"f": 1269}, {"f": 1269}, {"f": 1269}, {"f": 1269}, {"f": 1269}, {"f": 1269}, {"f": 1269}, {"f": 1269}, {"f": 1269}, {"f": 1269}, {"f": 1269}, {"f": 1269}, {"f": 1269}, {"f": 1269}, {"f": 1269}, {"f": 1269}, {"f": 1269}, {"f": 1269}, {"f": 1269}, {"f": 1269}, {"f": 1269}, {"f": 1269}, {"f": 1269}, {"f": 1269}, {"f": 1269}, {"f": 1269}, {"f": 1269}, {"f": 1269}, {"f": 1269}, {"f": 1269}, {"f": 1269}, {"f": 1269}, {"f": 1269}, {"f": 1269}, {"f": 1269}, {"f": 1269}, {"f": 1269}, {"f": 1269}, {"f": 1269}, {"f": 1269}], [{"f": 1269}, {"f": 1269}, {"f": 1269}, {"f": 1269}, {"f": 1269}, {"f": 1269}, {"f": 1269}, {"f": 1269}, {"f": 1269}, {"f": 1269}, {"f": 1269}, {"f": 1269}, {"f": 1269}, {"f": 1269}, {"f": 1269}, {"f": 1269}, {"f": 1269}, {"f": 1269}, {"f": 1269}, {"f": 1269}, {"f": 1269}, {"f": 1269}, {"f": 1269}, {"f": 1269}, {"f": 1269}, {"f": 1269}, {"f": 1269}, {"f": 1269}, {"f": 1269}, {"f": 1269}, {"f": 1269}, {"f": 1269}, {"f": 1269}, {"f": 1269}, {"f": 1269}, {"f": 1269}, {"f": 1269}, {"f": 1269}, {"f": 1269}, {"f": 1269}, {"f": 1269}, {"f": 1269}, {"f": 1269}, {"f": 1269}, {"f": 1269}, {"f": 1269}, {"f": 1269}, {"f": 1269}, {"f": 1269}, {"f": 1269}, {"f": 1269}, {"f": 1269}, {"f": 1269}, {"f": 1269}, {"f": 1269}, {"f": 1269}, {"f": 1269}, {"f": 1269}, {"f": 1269}, {"f": 1269}, {"f": 1269}, {"f": 1269}, {"f": 1269}, {"f": 1269}], [{"f": 1269}, {"f": 1269}, {"f": 1269}, {"f": 1269}, {"f": 1269}, {"f": 1269}, {"f": 1269}, {"f": 1269}, {"f": 1269}, {"f": 1269}, {"f": 1269}, {"f": 1269}, {"f": 1269}, {"f": 1269}, {"f": 1269}, {"f": 1269}, {"f": 1269}, {"f": 1269}, {"f": 1269}, {"f": 1269}, {"f": 1269}, {"f": 1269}, {"f": 1269}, {"f": 1269}, {"f": 1269}, {"f": 1269}, {"f": 1269}, {"f": 1269}, {"f": 1269}, {"f": 1269}, {"f": 1269}, {"f": 1269}, {"f": 1269}, {"f": 1269}, {"f": 1269}, {"f": 1269}, {"f": 1269}, {"f": 1269}, {"f": 1269}, {"f": 1269}, {"f": 1269}, {"f": 1269}, {"f": 1269}, {"f": 1269}, {"f": 1269}, {"f": 1269}, {"f": 1269}, {"f": 1269}, {"f": 1269}, {"f": 1269}, {"f": 1269}, {"f": 1269}, {"f": 1269}, {"f": 1269}, {"f": 1269}, {"f": 1269}, {"f": 1269}, {"f": 1269}, {"f": 1269}, {"f": 1269}, {"f": 1269}, {"f": 1269}, {"f": 1269}, {"f": 1269}], [{"f": 1269}, {"f": 1269}, {"f": 1269}, {"f": 1269}, {"f": 1269}, {"f": 1269}, {"f": 1269}, {"f": 1269}, {"f": 1269}, {"f": 1269}, {"f": 1269}, {"f": 1269}, {"f": 1269}, {"f": 1269}, {"f": 1269}, {"f": 1269}, {"f": 1269}, {"f": 1269}, {"f": 1269}, {"f": 1269}, {"f": 1269}, {"f": 1269}, {"f": 1269}, {"f": 1269}, {"f": 1269}, {"f": 1269}, {"f": 1269}, {"f": 1269}, {"f": 1269}, {"f": 1269}, {"f": 1269}, {"f": 1269}, {"f": 1269}, {"f": 1269}, {"f": 1269}, {"f": 1269}, {"f": 1269}, {"f": 1269}, {"f": 1269}, {"f": 1269}, {"f": 1269}, {"f": 1269}, {"f": 1269}, {"f": 1269}, {"f": 1269}, {"f": 1269}, {"f": 1269}, {"f": 1269}, {"f": 1269}, {"f": 1269}, {"f": 1269}, {"f": 1269}, {"f": 1269}, {"f": 1269}, {"f": 1269}, {"f": 1269}, {"f": 1269}, {"f": 1269}, {"f": 1269}, {"f": 1269}, {"f": 1269}, {"f": 1269}, {"f": 1269}, {"f": 1269}], [{"f": 1269}, {"f": 1269}, {"f": 1269}, {"f": 1269}, {"f": 1269}, {"f": 1269}, {"f": 1269}, {"f": 1269}, {"f": 1269}, {"f": 1269}, {"f": 1269}, {"f": 1269}, {"f": 1269}, {"f": 1269}, {"f": 1269}, {"f": 1269}, {"f": 1269}, {"f": 1269}, {"f": 1269}, {"f": 1269}, {"f": 1269}, {"f": 1269}, {"f": 1269}, {"f": 1269}, {"f": 1269}, {"f": 1269}, {"f": 1269}, {"f": 1269}, {"f": 1269}, {"f": 1269}, {"f": 1269}, {"f": 1269}, {"f": 1269}, {"f": 1269}, {"f": 1269}, {"f": 1269}, {"f": 1269}, {"f": 1269}, {"f": 1269}, {"f": 1269}, {"f": 1269}, {"f": 1269}, {"f": 1269}, {"f": 1269}, {"f": 1269}, {"f": 1269}, {"f": 1269}, {"f": 1269}, {"f": 1269}, {"f": 1269}, {"f": 1269}, {"f": 1269}, {"f": 1269}, {"f": 1269}, {"f": 1269}, {"f": 1269}, {"f": 1269}, {"f": 1269}, {"f": 1269}, {"f": 1269}, {"f": 1269}, {"f": 1269}, {"f": 1269}, {"f": 1269}], [{"f": 1269}, {"f": 1269}, {"f": 1269}, {"f": 1269}, {"f": 1269}, {"f": 1269}, {"f": 1269}, {"f": 1269}, {"f": 1269}, {"f": 1269}, {"f": 1269}, {"f": 1269}, {"f": 1269}, {"f": 1269}, {"f": 1269}, {"f": 1269}, {"f": 1269}, {"f": 1269}, {"f": 1269}, {"f": 1269}, {"f": 1269}, {"f": 1269}, {"f": 1269}, {"f": 1269}, {"f": 1269}, {"f": 1269}, {"f": 1269}, {"f": 1269}, {"f": 1269}, {"f": 1269}, {"f": 1269}, {"f": 1269}, {"f": 1269}, {"f": 1269}, {"f": 1269}, {"f": 1269}, {"f": 1269}, {"f": 1269}, {"f": 1269}, {"f": 1269}, {"f": 1269}, {"f": 1269}, {"f": 1269}, {"f": 1269}, {"f": 1269}, {"f": 1269}, {"f": 1269}, {"f": 1269}, {"f": 1269}, {"f": 1269}, {"f": 1269}, {"f": 1269}, {"f": 1269}, {"f": 1269}, {"f": 1269}, {"f": 1269}, {"f": 1269}, {"f": 1269}, {"f": 1269}, {"f": 1269}, {"f": 1269}, {"f": 1269}, {"f": 1269}, {"f": 1269}], [{"f": 1269}, {"f": 1269}, {"f": 1269}, {"f": 1269}, {"f": 1269}, {"f": 1269}, {"f": 1269}, {"f": 1269}, {"f": 1269}, {"f": 1269}, {"f": 1269}, {"f": 1269}, {"f": 1269}, {"f": 1269}, {"f": 1269}, {"f": 1269}, {"f": 1269}, {"f": 1269}, {"f": 1269}, {"f": 1269}, {"f": 1269}, {"f": 1269}, {"f": 1269}, {"f": 1269}, {"f": 1269}, {"f": 1269}, {"f": 1269}, {"f": 1269}, {"f": 1269}, {"f": 1269}, {"f": 1269}, {"f": 1269}, {"f": 1269}, {"f": 1269}, {"f": 1269}, {"f": 1269}, {"f": 1269}, {"f": 1269}, {"f": 1269}, {"f": 1269}, {"f": 1269}, {"f": 1269}, {"f": 1269}, {"f": 1269}, {"f": 1269}, {"f": 1269}, {"f": 1269}, {"f": 1269}, {"f": 1269}, {"f": 1269}, {"f": 1269}, {"f": 1269}, {"f": 1269}, {"f": 1269}, {"f": 1269}, {"f": 1269}, {"f": 1269}, {"f": 1269}, {"f": 1269}, {"f": 1269}, {"f": 1269}, {"f": 1269}, {"f": 1269}, {"f": 1269}], [{"f": 1269}, {"f": 1269}, {"f": 1269}, {"f": 1269}, {"f": 1269}, {"f": 1269}, {"f": 1269}, {"f": 1269}, {"f": 1269}, {"f": 1269}, {"f": 1269}, {"f": 1269}, {"f": 1269}, {"f": 1269}, {"f": 1269}, {"f": 1269}, {"f": 1269}, {"f": 1269}, {"f": 1269}, {"f": 1269}, {"f": 1269}, {"f": 1269}, {"f": 1269}, {"f": 1269}, {"f": 1269}, {"f": 1269}, {"f": 1269}, {"f": 1269}, {"f": 1269}, {"f": 1269}, {"f": 1269}, {"f": 1269}, {"f": 1269}, {"f": 1269}, {"f": 1269}, {"f": 1269}, {"f": 1269}, {"f": 1269}, {"f": 1269}, {"f": 1269}, {"f": 1269}, {"f": 1269}, {"f": 1269}, {"f": 1269}, {"f": 1269}, {"f": 1269}, {"f": 1269}, {"f": 1269}, {"f": 1269}, {"f": 1269}, {"f": 1269}, {"f": 1269}, {"f": 1269}, {"f": 1269}, {"f": 1269}, {"f": 1269}, {"f": 1269}, {"f": 1269}, {"f": 1269}, {"f": 1269}, {"f": 1269}, {"f": 1269}, {"f": 1269}, {"f": 1269}], [{"f": 1269}, {"f": 1269}, {"f": 1269}, {"f": 1269}, {"f": 1269}, {"f": 1269}, {"f": 1269}, {"f": 1269}, {"f": 1269}, {"f": 1269}, {"f": 1269}, {"f": 1269}, {"f": 1269}, {"f": 1269}, {"f": 1269}, {"f": 1269}, {"f": 1269}, {"f": 1269}, {"f": 1269}, {"f": 1269}, {"f": 1269}, {"f": 1269}, {"f": 1269}, {"f": 1269}, {"f": 1269}, {"f": 1269}, {"f": 1269}, {"f": 1269}, {"f": 1269}, {"f": 1269}, {"f": 1269}, {"f": 1269}, {"f": 1269}, {"f": 1269}, {"f": 1269}, {"f": 1269}, {"f": 1269}, {"f": 1269}, {"f": 1269}, {"f": 1269}, {"f": 1269}, {"f": 1269}, {"f": 1269}, {"f": 1269}, {"f": 1269}, {"f": 1269}, {"f": 1269}, {"f": 1269}, {"f": 1269}, {"f": 1269}, {"f": 1269}, {"f": 1269}, {"f": 1269}, {"f": 1269}, {"f": 1269}, {"f": 1269}, {"f": 1269}, {"f": 1269}, {"f": 1269}, {"f": 1269}, {"f": 1269}, {"f": 1269}, {"f": 1269}, {"f": 1269}], [{"f": 1269}, {"f": 1269}, {"f": 1269}, {"f": 1269}, {"f": 1269}, {"f": 1269}, {"f": 1269}, {"f": 1269}, {"f": 1269}, {"f": 1269}, {"f": 1269}, {"f": 1269}, {"f": 1269}, {"f": 1269}, {"f": 1269}, {"f": 1269}, {"f": 1269}, {"f": 1269}, {"f": 1269}, {"f": 1269}, {"f": 1269}, {"f": 1269}, {"f": 1269}, {"f": 1269}, {"f": 1269}, {"f": 1269}, {"f": 1269}, {"f": 1269}, {"f": 1269}, {"f": 1269}, {"f": 1269}, {"f": 1269}, {"f": 1269}, {"f": 1269}, {"f": 1269}, {"f": 1269}, {"f": 1269}, {"f": 1269}, {"f": 1269}, {"f": 1269}, {"f": 1269}, {"f": 1269}, {"f": 1269}, {"f": 1269}, {"f": 1269}, {"f": 1269}, {"f": 1269}, {"f": 1269}, {"f": 1269}, {"f": 1269}, {"f": 1269}, {"f": 1269}, {"f": 1269}, {"f": 1269}, {"f": 1269}, {"f": 1269}, {"f": 1269}, {"f": 1269}, {"f": 1269}, {"f": 1269}, {"f": 1269}, {"f": 1269}, {"f": 1269}, {"f": 1269}], [{"f": 1269}, {"f": 1269}, {"f": 1269}, {"f": 1269}, {"f": 1269}, {"f": 1269}, {"f": 1269}, {"f": 1269}, {"f": 1269}, {"f": 1269}, {"f": 1269}, {"f": 1269}, {"f": 1269}, {"f": 1269}, {"f": 1269}, {"f": 1269}, {"f": 1269}, {"f": 1269}, {"f": 1269}, {"f": 1269}, {"f": 1269}, {"f": 1269}, {"f": 1269}, {"f": 1269}, {"f": 1269}, {"f": 1269}, {"f": 1269}, {"f": 1269}, {"f": 1269}, {"f": 1269}, {"f": 1269}, {"f": 1269}, {"f": 1269}, {"f": 1269}, {"f": 1269}, {"f": 1269}, {"f": 1269}, {"f": 1269}, {"f": 1269}, {"f": 1269}, {"f": 1269}, {"f": 1269}, {"f": 1269}, {"f": 1269}, {"f": 1269}, {"f": 1269}, {"f": 1269}, {"f": 1269}, {"f": 1269}, {"f": 1269}, {"f": 1269}, {"f": 1269}, {"f": 1269}, {"f": 1269}, {"f": 1269}, {"f": 1269}, {"f": 1269}, {"f": 1269}, {"f": 1269}, {"f": 1269}, {"f": 1269}, {"f": 1269}, {"f": 1269}, {"f": 1269}], [{"f": 1269}, {"f": 1269}, {"f": 1269}, {"f": 1269}, {"f": 1269}, {"f": 1269}, {"f": 1269}, {"f": 1269}, {"f": 1269}, {"f": 1269}, {"f": 1269}, {"f": 1269}, {"f": 1269}, {"f": 1269}, {"f": 1269}, {"f": 1269}, {"f": 1269}, {"f": 1269}, {"f": 1269}, {"f": 1269}, {"f": 1269}, {"f": 1269}, {"f": 1269}, {"f": 1269}, {"f": 1269}, {"f": 1269}, {"f": 1269}, {"f": 1269}, {"f": 1269}, {"f": 1269}, {"f": 1269}, {"f": 1269}, {"f": 1269}, {"f": 1269}, {"f": 1269}, {"f": 1269}, {"f": 1269}, {"f": 1269}, {"f": 1269}, {"f": 1269}, {"f": 1269}, {"f": 1269}, {"f": 1269}, {"f": 1269}, {"f": 1269}, {"f": 1269}, {"f": 1269}, {"f": 1269}, {"f": 1269}, {"f": 1269}, {"f": 1269}, {"f": 1269}, {"f": 1269}, {"f": 1269}, {"f": 1269}, {"f": 1269}, {"f": 1269}, {"f": 1269}, {"f": 1269}, {"f": 1269}, {"f": 1269}, {"f": 1269}, {"f": 1269}, {"f": 1269}], [{"f": 1269}, {"f": 1269}, {"f": 1269}, {"f": 1269}, {"f": 1269}, {"f": 1269}, {"f": 1269}, {"f": 1269}, {"f": 1269}, {"f": 1269}, {"f": 1269}, {"f": 1269}, {"f": 1269}, {"f": 1269}, {"f": 1269}, {"f": 1269}, {"f": 1269}, {"f": 1269}, {"f": 1269}, {"f": 1269}, {"f": 1269}, {"f": 1269}, {"f": 1269}, {"f": 1269}, {"f": 1269}, {"f": 1269}, {"f": 1269}, {"f": 1269}, {"f": 1269}, {"f": 1269}, {"f": 1269}, {"f": 1269}, {"f": 1269}, {"f": 1269}, {"f": 1269}, {"f": 1269}, {"f": 1269}, {"f": 1269}, {"f": 1269}, {"f": 1269}, {"f": 1269}, {"f": 1269}, {"f": 1269}, {"f": 1269}, {"f": 1269}, {"f": 1269}, {"f": 1269}, {"f": 1269}, {"f": 1269}, {"f": 1269}, {"f": 1269}, {"f": 1269}, {"f": 1269}, {"f": 1269}, {"f": 1269}, {"f": 1269}, {"f": 1269}, {"f": 1269}, {"f": 1269}, {"f": 1269}, {"f": 1269}, {"f": 1269}, {"f": 1269}, {"f": 1269}], [{"f": 1269}, {"f": 1269}, {"f": 1269}, {"f": 1269}, {"f": 1269}, {"f": 1269}, {"f": 1269}, {"f": 1269}, {"f": 1269}, {"f": 1269}, {"f": 1269}, {"f": 1269}, {"f": 1269}, {"f": 1269}, {"f": 1269}, {"f": 1269}, {"f": 1269}, {"f": 1269}, {"f": 1269}, {"f": 1269}, {"f": 1269}, {"f": 1269}, {"f": 1269}, {"f": 1269}, {"f": 1269}, {"f": 1269}, {"f": 1269}, {"f": 1269}, {"f": 1269}, {"f": 1269}, {"f": 1269}, {"f": 1269}, {"f": 1269}, {"f": 1269}, {"f": 1269}, {"f": 1269}, {"f": 1269}, {"f": 1269}, {"f": 1269}, {"f": 1269}, {"f": 1269}, {"f": 1269}, {"f": 1269}, {"f": 1269}, {"f": 1269}, {"f": 1269}, {"f": 1269}, {"f": 1269}, {"f": 1269}, {"f": 1269}, {"f": 1269}, {"f": 1269}, {"f": 1269}, {"f": 1269}, {"f": 1269}, {"f": 1269}, {"f": 1269}, {"f": 1269}, {"f": 1269}, {"f": 1269}, {"f": 1269}, {"f": 1269}, {"f": 1269}, {"f": 1269}], [{"f": 1269}, {"f": 1269}, {"f": 1269}, {"f": 1269}, {"f": 1269}, {"f": 1269}, {"f": 1269}, {"f": 1269}, {"f": 1269}, {"f": 1269}, {"f": 1269}, {"f": 1269}, {"f": 1269}, {"f": 1269}, {"f": 1269}, {"f": 1269}, {"f": 1269}, {"f": 1269}, {"f": 1269}, {"f": 1269}, {"f": 1269}, {"f": 1269}, {"f": 1269}, {"f": 1269}, {"f": 1269}, {"f": 1269}, {"f": 1269}, {"f": 1269}, {"f": 1269}, {"f": 1269}, {"f": 1269}, {"f": 1269}, {"f": 1269}, {"f": 1269}, {"f": 1269}, {"f": 1269}, {"f": 1269}, {"f": 1269}, {"f": 1269}, {"f": 1269}, {"f": 1269}, {"f": 1269}, {"f": 1269}, {"f": 1269}, {"f": 1269}, {"f": 1269}, {"f": 1269}, {"f": 1269}, {"f": 1269}, {"f": 1269}, {"f": 1269}, {"f": 1269}, {"f": 1269}, {"f": 1269}, {"f": 1269}, {"f": 1269}, {"f": 1269}, {"f": 1269}, {"f": 1269}, {"f": 1269}, {"f": 1269}, {"f": 1269}, {"f": 1269}, {"f": 1269}], [{"f": 1269}, {"f": 1269}, {"f": 1269}, {"f": 1269}, {"f": 1269}, {"f": 1269}, {"f": 1269}, {"f": 1269}, {"f": 1269}, {"f": 1269}, {"f": 1269}, {"f": 1269}, {"f": 1269}, {"f": 1269}, {"f": 1269}, {"f": 1269}, {"f": 1269}, {"f": 1269}, {"f": 1269}, {"f": 1269}, {"f": 1269}, {"f": 1269}, {"f": 1269}, {"f": 1269}, {"f": 1269}, {"f": 1269}, {"f": 1269}, {"f": 1269}, {"f": 1269}, {"f": 1269}, {"f": 1269}, {"f": 1269}, {"f": 1269}, {"f": 1269}, {"f": 1269}, {"f": 1269}, {"f": 1269}, {"f": 1269}, {"f": 1269}, {"f": 1269}, {"f": 1269}, {"f": 1269}, {"f": 1269}, {"f": 1269}, {"f": 1269}, {"f": 1269}, {"f": 1269}, {"f": 1269}, {"f": 1269}, {"f": 1269}, {"f": 1269}, {"f": 1269}, {"f": 1269}, {"f": 1269}, {"f": 1269}, {"f": 1269}, {"f": 1269}, {"f": 1269}, {"f": 1269}, {"f": 1269}, {"f": 1269}, {"f": 1269}, {"f": 1269}, {"f": 1269}], [{"f": 1269}, {"f": 1269}, {"f": 1269}, {"f": 1269}, {"f": 1269}, {"f": 1269}, {"f": 1269}, {"f": 1269}, {"f": 1269}, {"f": 1269}, {"f": 1269}, {"f": 1269}, {"f": 1269}, {"f": 1269}, {"f": 1269}, {"f": 1269}, {"f": 1269}, {"f": 1269}, {"f": 1269}, {"f": 1269}, {"f": 1269}, {"f": 1269}, {"f": 1269}, {"f": 1269}, {"f": 1269}, {"f": 1269}, {"f": 1269}, {"f": 1269}, {"f": 1269}, {"f": 1269}, {"f": 1269}, {"f": 1269}, {"f": 1269}, {"f": 1269}, {"f": 1269}, {"f": 1269}, {"f": 1269}, {"f": 1269}, {"f": 1269}, {"f": 1269}, {"f": 1269}, {"f": 1269}, {"f": 1269}, {"f": 1269}, {"f": 1269}, {"f": 1269}, {"f": 1269}, {"f": 1269}, {"f": 1269}, {"f": 1269}, {"f": 1269}, {"f": 1269}, {"f": 1269}, {"f": 1269}, {"f": 1269}, {"f": 1269}, {"f": 1269}, {"f": 1269}, {"f": 1269}, {"f": 1269}, {"f": 1269}, {"f": 1269}, {"f": 1269}, {"f": 1269}], [{"f": 1269}, {"f": 1269}, {"f": 1269}, {"f": 1269}, {"f": 1269}, {"f": 1269}, {"f": 1269}, {"f": 1269}, {"f": 1269}, {"f": 1269}, {"f": 1269}, {"f": 1269}, {"f": 1269}, {"f": 1269}, {"f": 1269}, {"f": 1269}, {"f": 1269}, {"f": 1269}, {"f": 1269}, {"f": 1269}, {"f": 1269}, {"f": 1269}, {"f": 1269}, {"f": 1269}, {"f": 1269}, {"f": 1269}, {"f": 1269}, {"f": 1269}, {"f": 1269}, {"f": 1269}, {"f": 1269}, {"f": 1269}, {"f": 1269}, {"f": 1269}, {"f": 1269}, {"f": 1269}, {"f": 1269}, {"f": 1269}, {"f": 1269}, {"f": 1269}, {"f": 1269}, {"f": 1269}, {"f": 1269}, {"f": 1269}, {"f": 1269}, {"f": 1269}, {"f": 1269}, {"f": 1269}, {"f": 1269}, {"f": 1269}, {"f": 1269}, {"f": 1269}, {"f": 1269}, {"f": 1269}, {"f": 1269}, {"f": 1269}, {"f": 1269}, {"f": 1269}, {"f": 1269}, {"f": 1269}, {"f": 1269}, {"f": 1269}, {"f": 1269}, {"f": 1269}], [{"f": 1269}, {"f": 1269}, {"f": 1269}, {"f": 1269}, {"f": 1269}, {"f": 1269}, {"f": 1269}, {"f": 1269}, {"f": 1269}, {"f": 1269}, {"f": 1269}, {"f": 1269}, {"f": 1269}, {"f": 1269}, {"f": 1269}, {"f": 1269}, {"f": 1269}, {"f": 1269}, {"f": 1269}, {"f": 1269}, {"f": 1269}, {"f": 1269}, {"f": 1269}, {"f": 1269}, {"f": 1269}, {"f": 1269}, {"f": 1269}, {"f": 1269}, {"f": 1269}, {"f": 1269}, {"f": 1269}, {"f": 1269}, {"f": 1269}, {"f": 1269}, {"f": 1269}, {"f": 1269}, {"f": 1269}, {"f": 1269}, {"f": 1269}, {"f": 1269}, {"f": 1269}, {"f": 1269}, {"f": 1269}, {"f": 1269}, {"f": 1269}, {"f": 1269}, {"f": 1269}, {"f": 1269}, {"f": 1269}, {"f": 1269}, {"f": 1269}, {"f": 1269}, {"f": 1269}, {"f": 1269}, {"f": 1269}, {"f": 1269}, {"f": 1269}, {"f": 1269}, {"f": 1269}, {"f": 1269}, {"f": 1269}, {"f": 1269}, {"f": 1269}, {"f": 1269}], [{"f": 1269}, {"f": 1269}, {"f": 1269}, {"f": 1269}, {"f": 1269}, {"f": 1269}, {"f": 1269}, {"f": 1269}, {"f": 1269}, {"f": 1269}, {"f": 1269}, {"f": 1269}, {"f": 1269}, {"f": 1269}, {"f": 1269}, {"f": 1269}, {"f": 1269}, {"f": 1269}, {"f": 1269}, {"f": 1269}, {"f": 1269}, {"f": 1269}, {"f": 1269}, {"f": 1269}, {"f": 1269}, {"f": 1269}, {"f": 1269}, {"f": 1269}, {"f": 1269}, {"f": 1269}, {"f": 1269}, {"f": 1269}, {"f": 1269}, {"f": 1269}, {"f": 1269}, {"f": 1269}, {"f": 1269}, {"f": 1269}, {"f": 1269}, {"f": 1269}, {"f": 1269}, {"f": 1269}, {"f": 1269}, {"f": 1269}, {"f": 1269}, {"f": 1269}, {"f": 1269}, {"f": 1269}, {"f": 1269}, {"f": 1269}, {"f": 1269}, {"f": 1269}, {"f": 1269}, {"f": 1269}, {"f": 1269}, {"f": 1269}, {"f": 1269}, {"f": 1269}, {"f": 1269}, {"f": 1269}, {"f": 1269}, {"f": 1269}, {"f": 1269}, {"f": 1269}], [{"f": 1269}, {"f": 1269}, {"f": 1269}, {"f": 1269}, {"f": 1269}, {"f": 1269}, {"f": 1269}, {"f": 1269}, {"f": 1269}, {"f": 1269}, {"f": 1269}, {"f": 1269}, {"f": 1269}, {"f": 1269}, {"f": 1269}, {"f": 1269}, {"f": 1269}, {"f": 1269}, {"f": 1269}, {"f": 1269}, {"f": 1269}, {"f": 1269}, {"f": 1269}, {"f": 1269}, {"f": 1269}, {"f": 1269}, {"f": 1269}, {"f": 1269}, {"f": 1269}, {"f": 1269}, {"f": 1269}, {"f": 1269}, {"f": 1269}, {"f": 1269}, {"f": 1269}, {"f": 1269}, {"f": 1269}, {"f": 1269}, {"f": 1269}, {"f": 1269}, {"f": 1269}, {"f": 1269}, {"f": 1269}, {"f": 1269}, {"f": 1269}, {"f": 1269}, {"f": 1269}, {"f": 1269}, {"f": 1269}, {"f": 1269}, {"f": 1269}, {"f": 1269}, {"f": 1269}, {"f": 1269}, {"f": 1269}, {"f": 1269}, {"f": 1269}, {"f": 1269}, {"f": 1269}, {"f": 1269}, {"f": 1269}, {"f": 1269}, {"f": 1269}, {"f": 1269}], [{"f": 1269}, {"f": 1269}, {"f": 1269}, {"f": 1269}, {"f": 1269}, {"f": 1269}, {"f": 1269}, {"f": 1269}, {"f": 1269}, {"f": 1269}, {"f": 1269}, {"f": 1269}, {"f": 1269}, {"f": 1269}, {"f": 1269}, {"f": 1269}, {"f": 1269}, {"f": 1269}, {"f": 1269}, {"f": 1269}, {"f": 1269}, {"f": 1269}, {"f": 1269}, {"f": 1269}, {"f": 1269}, {"f": 1269}, {"f": 1269}, {"f": 1269}, {"f": 1269}, {"f": 1269}, {"f": 1269}, {"f": 1269}, {"f": 1269}, {"f": 1269}, {"f": 1269}, {"f": 1269}, {"f": 1269}, {"f": 1269}, {"f": 1269}, {"f": 1269}, {"f": 1269}, {"f": 1269}, {"f": 1269}, {"f": 1269}, {"f": 1269}, {"f": 1269}, {"f": 1269}, {"f": 1269}, {"f": 1269}, {"f": 1269}, {"f": 1269}, {"f": 1269}, {"f": 1269}, {"f": 1269}, {"f": 1269}, {"f": 1269}, {"f": 1269}, {"f": 1269}, {"f": 1269}, {"f": 1269}, {"f": 1269}, {"f": 1269}, {"f": 1269}, {"f": 1269}], [{"f": 1269}, {"f": 1269}, {"f": 1269}, {"f": 1269}, {"f": 1269}, {"f": 1269}, {"f": 1269}, {"f": 1269}, {"f": 1269}, {"f": 1269}, {"f": 1269}, {"f": 1269}, {"f": 1269}, {"f": 1269}, {"f": 1269}, {"f": 1269}, {"f": 1269}, {"f": 1269}, {"f": 1269}, {"f": 1269}, {"f": 1269}, {"f": 1269}, {"f": 1269}, {"f": 1269}, {"f": 1269}, {"f": 1269}, {"f": 1269}, {"f": 1269}, {"f": 1269}, {"f": 1269}, {"f": 1269}, {"f": 1269}, {"f": 1269}, {"f": 1269}, {"f": 1269}, {"f": 1269}, {"f": 1269}, {"f": 1269}, {"f": 1269}, {"f": 1269}, {"f": 1269}, {"f": 1269}, {"f": 1269}, {"f": 1269}, {"f": 1269}, {"f": 1269}, {"f": 1269}, {"f": 1269}, {"f": 1269}, {"f": 1269}, {"f": 1269}, {"f": 1269}, {"f": 1269}, {"f": 1269}, {"f": 1269}, {"f": 1269}, {"f": 1269}, {"f": 1269}, {"f": 1269}, {"f": 1269}, {"f": 1269}, {"f": 1269}, {"f": 1269}, {"f": 1269}], [{"f": 1269}, {"f": 1269}, {"f": 1269}, {"f": 1269}, {"f": 1269}, {"f": 1269}, {"f": 1269}, {"f": 1269}, {"f": 1269}, {"f": 1269}, {"f": 1269}, {"f": 1269}, {"f": 1269}, {"f": 1269}, {"f": 1269}, {"f": 1269}, {"f": 1269}, {"f": 1269}, {"f": 1269}, {"f": 1269}, {"f": 1269}, {"f": 1269}, {"f": 1269}, {"f": 1269}, {"f": 1269}, {"f": 1269}, {"f": 1269}, {"f": 1269}, {"f": 1269}, {"f": 1269}, {"f": 1269}, {"f": 1269}, {"f": 1269}, {"f": 1269}, {"f": 1269}, {"f": 1269}, {"f": 1269}, {"f": 1269}, {"f": 1269}, {"f": 1269}, {"f": 1269}, {"f": 1269}, {"f": 1269}, {"f": 1269}, {"f": 1269}, {"f": 1269}, {"f": 1269}, {"f": 1269}, {"f": 1269}, {"f": 1269}, {"f": 1269}, {"f": 1269}, {"f": 1269}, {"f": 1269}, {"f": 1269}, {"f": 1269}, {"f": 1269}, {"f": 1269}, {"f": 1269}, {"f": 1269}, {"f": 1269}, {"f": 1269}, {"f": 1269}, {"f": 1269}], [{"f": 1269}, {"f": 1269}, {"f": 1269}, {"f": 1269}, {"f": 1269}, {"f": 1269}, {"f": 1269}, {"f": 1269}, {"f": 1269}, {"f": 1269}, {"f": 1269}, {"f": 1269}, {"f": 1269}, {"f": 1269}, {"f": 1269}, {"f": 1269}, {"f": 1269}, {"f": 1269}, {"f": 1269}, {"f": 1269}, {"f": 1269}, {"f": 1269}, {"f": 1269}, {"f": 1269}, {"f": 1269}, {"f": 1269}, {"f": 1269}, {"f": 1269}, {"f": 1269}, {"f": 1269}, {"f": 1269}, {"f": 1269}, {"f": 1269}, {"f": 1269}, {"f": 1269}, {"f": 1269}, {"f": 1269}, {"f": 1269}, {"f": 1269}, {"f": 1269}, {"f": 1269}, {"f": 1269}, {"f": 1269}, {"f": 1269}, {"f": 1269}, {"f": 1269}, {"f": 1269}, {"f": 1269}, {"f": 1269}, {"f": 1269}, {"f": 1269}, {"f": 1269}, {"f": 1269}, {"f": 1269}, {"f": 1269}, {"f": 1269}, {"f": 1269}, {"f": 1269}, {"f": 1269}, {"f": 1269}, {"f": 1269}, {"f": 1269}, {"f": 1269}, {"f": 1269}], [{"f": 1269}, {"f": 1269}, {"f": 1269}, {"f": 1269}, {"f": 1269}, {"f": 1269}, {"f": 1269}, {"f": 1269}, {"f": 1269}, {"f": 1269}, {"f": 1269}, {"f": 1269}, {"f": 1269}, {"f": 1269}, {"f": 1269}, {"f": 1269}, {"f": 1269}, {"f": 1269}, {"f": 1269}, {"f": 1269}, {"f": 1269}, {"f": 1269}, {"f": 1269}, {"f": 1269}, {"f": 1269}, {"f": 1269}, {"f": 1269}, {"f": 1269}, {"f": 1269}, {"f": 1269}, {"f": 1269}, {"f": 1269}, {"f": 1269}, {"f": 1269}, {"f": 1269}, {"f": 1269}, {"f": 1269}, {"f": 1269}, {"f": 1269}, {"f": 1269}, {"f": 1269}, {"f": 1269}, {"f": 1269}, {"f": 1269}, {"f": 1269}, {"f": 1269}, {"f": 1269}, {"f": 1269}, {"f": 1269}, {"f": 1269}, {"f": 1269}, {"f": 1269}, {"f": 1269}, {"f": 1269}, {"f": 1269}, {"f": 1269}, {"f": 1269}, {"f": 1269}, {"f": 1269}, {"f": 1269}, {"f": 1269}, {"f": 1269}, {"f": 1269}, {"f": 1269}], [{"f": 1269}, {"f": 1269}, {"f": 1269}, {"f": 1269}, {"f": 1269}, {"f": 1269}, {"f": 1269}, {"f": 1269}, {"f": 1269}, {"f": 1269}, {"f": 1269}, {"f": 1269}, {"f": 1269}, {"f": 1269}, {"f": 1269}, {"f": 1269}, {"f": 1269}, {"f": 1269}, {"f": 1269}, {"f": 1269}, {"f": 1269}, {"f": 1269}, {"f": 1269}, {"f": 1269}, {"f": 1269}, {"f": 1269}, {"f": 1269}, {"f": 1269}, {"f": 1269}, {"f": 1269}, {"f": 1269}, {"f": 1269}, {"f": 1269}, {"f": 1269}, {"f": 1269}, {"f": 1269}, {"f": 1269}, {"f": 1269}, {"f": 1269}, {"f": 1269}, {"f": 1269}, {"f": 1269}, {"f": 1269}, {"f": 1269}, {"f": 1269}, {"f": 1269}, {"f": 1269}, {"f": 1269}, {"f": 1269}, {"f": 1269}, {"f": 1269}, {"f": 1269}, {"f": 1269}, {"f": 1269}, {"f": 1269}, {"f": 1269}, {"f": 1269}, {"f": 1269}, {"f": 1269}, {"f": 1269}, {"f": 1269}, {"f": 1269}, {"f": 1269}, {"f": 1269}], [{"f": 1269}, {"f": 1269}, {"f": 1269}, {"f": 1269}, {"f": 1269}, {"f": 1269}, {"f": 1269}, {"f": 1269}, {"f": 1269}, {"f": 1269}, {"f": 1269}, {"f": 1269}, {"f": 1269}, {"f": 1269}, {"f": 1269}, {"f": 1269}, {"f": 1269}, {"f": 1269}, {"f": 1269}, {"f": 1269}, {"f": 1269}, {"f": 1269}, {"f": 1269}, {"f": 1269}, {"f": 1269}, {"f": 1269}, {"f": 1269}, {"f": 1269}, {"f": 1269}, {"f": 1269}, {"f": 1269}, {"f": 1269}, {"f": 1269}, {"f": 1269}, {"f": 1269}, {"f": 1269}, {"f": 1269}, {"f": 1269}, {"f": 1269}, {"f": 1269}, {"f": 1269}, {"f": 1269}, {"f": 1269}, {"f": 1269}, {"f": 1269}, {"f": 1269}, {"f": 1269}, {"f": 1269}, {"f": 1269}, {"f": 1269}, {"f": 1269}, {"f": 1269}, {"f": 1269}, {"f": 1269}, {"f": 1269}, {"f": 1269}, {"f": 1269}, {"f": 1269}, {"f": 1269}, {"f": 1269}, {"f": 1269}, {"f": 1269}, {"f": 1269}, {"f": 1269}], [{"f": 1269}, {"f": 1269}, {"f": 1269}, {"f": 1269}, {"f": 1269}, {"f": 1269}, {"f": 1269}, {"f": 1269}, {"f": 1269}, {"f": 1269}, {"f": 1269}, {"f": 1269}, {"f": 1269}, {"f": 1269}, {"f": 1269}, {"f": 1269}, {"f": 1269}, {"f": 1269}, {"f": 1269}, {"f": 1269}, {"f": 1269}, {"f": 1269}, {"f": 1269}, {"f": 1269}, {"f": 1269}, {"f": 1269}, {"f": 1269}, {"f": 1269}, {"f": 1269}, {"f": 1269}, {"f": 1269}, {"f": 1269}, {"f": 1269}, {"f": 1269}, {"f": 1269}, {"f": 1269}, {"f": 1269}, {"f": 1269}, {"f": 1269}, {"f": 1269}, {"f": 1269}, {"f": 1269}, {"f": 1269}, {"f": 1269}, {"f": 1269}, {"f": 1269}, {"f": 1269}, {"f": 1269}, {"f": 1269}, {"f": 1269}, {"f": 1269}, {"f": 1269}, {"f": 1269}, {"f": 1269}, {"f": 1269}, {"f": 1269}, {"f": 1269}, {"f": 1269}, {"f": 1269}, {"f": 1269}, {"f": 1269}, {"f": 1269}, {"f": 1269}, {"f": 1269}], [{"f": 1269}, {"f": 1269}, {"f": 1269}, {"f": 1269}, {"f": 1269}, {"f": 1269}, {"f": 1269}, {"f": 1269}, {"f": 1269}, {"f": 1269}, {"f": 1269}, {"f": 1269}, {"f": 1269}, {"f": 1269}, {"f": 1269}, {"f": 1269}, {"f": 1269}, {"f": 1269}, {"f": 1269}, {"f": 1269}, {"f": 1269}, {"f": 1269}, {"f": 1269}, {"f": 1269}, {"f": 1269}, {"f": 1269}, {"f": 1269}, {"f": 1269}, {"f": 1269}, {"f": 1269}, {"f": 1269}, {"f": 1269}, {"f": 1269}, {"f": 1269}, {"f": 1269}, {"f": 1269}, {"f": 1269}, {"f": 1269}, {"f": 1269}, {"f": 1269}, {"f": 1269}, {"f": 1269}, {"f": 1269}, {"f": 1269}, {"f": 1269}, {"f": 1269}, {"f": 1269}, {"f": 1269}, {"f": 1269}, {"f": 1269}, {"f": 1269}, {"f": 1269}, {"f": 1269}, {"f": 1269}, {"f": 1269}, {"f": 1269}, {"f": 1269}, {"f": 1269}, {"f": 1269}, {"f": 1269}, {"f": 1269}, {"f": 1269}, {"f": 1269}, {"f": 1269}], [{"f": 1269}, {"f": 1269}, {"f": 1269}, {"f": 1269}, {"f": 1269}, {"f": 1269}, {"f": 1269}, {"f": 1269}, {"f": 1269}, {"f": 1269}, {"f": 1269}, {"f": 1269}, {"f": 1269}, {"f": 1269}, {"f": 1269}, {"f": 1269}, {"f": 1269}, {"f": 1269}, {"f": 1269}, {"f": 1269}, {"f": 1269}, {"f": 1269}, {"f": 1269}, {"f": 1269}, {"f": 1269}, {"f": 1269}, {"f": 1269}, {"f": 1269}, {"f": 1269}, {"f": 1269}, {"f": 1269}, {"f": 1269}, {"f": 1269}, {"f": 1269}, {"f": 1269}, {"f": 1269}, {"f": 1269}, {"f": 1269}, {"f": 1269}, {"f": 1269}, {"f": 1269}, {"f": 1269}, {"f": 1269}, {"f": 1269}, {"f": 1269}, {"f": 1269}, {"f": 1269}, {"f": 1269}, {"f": 1269}, {"f": 1269}, {"f": 1269}, {"f": 1269}, {"f": 1269}, {"f": 1269}, {"f": 1269}, {"f": 1269}, {"f": 1269}, {"f": 1269}, {"f": 1269}, {"f": 1269}, {"f": 1269}, {"f": 1269}, {"f": 1269}, {"f": 1269}], [{"f": 1269}, {"f": 1269}, {"f": 1269}, {"f": 1269}, {"f": 1269}, {"f": 1269}, {"f": 1269}, {"f": 1269}, {"f": 1269}, {"f": 1269}, {"f": 1269}, {"f": 1269}, {"f": 1269}, {"f": 1269}, {"f": 1269}, {"f": 1269}, {"f": 1269}, {"f": 1269}, {"f": 1269}, {"f": 1269}, {"f": 1269}, {"f": 1269}, {"f": 1269}, {"f": 1269}, {"f": 1269}, {"f": 1269}, {"f": 1269}, {"f": 1269}, {"f": 1269}, {"f": 1269}, {"f": 1269}, {"f": 1269}, {"f": 1269}, {"f": 1269}, {"f": 1269}, {"f": 1269}, {"f": 1269}, {"f": 1269}, {"f": 1269}, {"f": 1269}, {"f": 1269}, {"f": 1269}, {"f": 1269}, {"f": 1269}, {"f": 1269}, {"f": 1269}, {"f": 1269}, {"f": 1269}, {"f": 1269}, {"f": 1269}, {"f": 1269}, {"f": 1269}, {"f": 1269}, {"f": 1269}, {"f": 1269}, {"f": 1269}, {"f": 1269}, {"f": 1269}, {"f": 1269}, {"f": 1269}, {"f": 1269}, {"f": 1269}, {"f": 1269}, {"f": 1269}], [{"f": 1269}, {"f": 1269}, {"f": 1269}, {"f": 1269}, {"f": 1269}, {"f": 1269}, {"f": 1269}, {"f": 1269}, {"f": 1269}, {"f": 1269}, {"f": 1269}, {"f": 1269}, {"f": 1269}, {"f": 1269}, {"f": 1269}, {"f": 1269}, {"f": 1269}, {"f": 1269}, {"f": 1269}, {"f": 1269}, {"f": 1269}, {"f": 1269}, {"f": 1269}, {"f": 1269}, {"f": 1269}, {"f": 1269}, {"f": 1269}, {"f": 1269}, {"f": 1269}, {"f": 1269}, {"f": 1269}, {"f": 1269}, {"f": 1269}, {"f": 1269}, {"f": 1269}, {"f": 1269}, {"f": 1269}, {"f": 1269}, {"f": 1269}, {"f": 1269}, {"f": 1269}, {"f": 1269}, {"f": 1269}, {"f": 1269}, {"f": 1269}, {"f": 1269}, {"f": 1269}, {"f": 1269}, {"f": 1269}, {"f": 1269}, {"f": 1269}, {"f": 1269}, {"f": 1269}, {"f": 1269}, {"f": 1269}, {"f": 1269}, {"f": 1269}, {"f": 1269}, {"f": 1269}, {"f": 1269}, {"f": 1269}, {"f": 1269}, {"f": 1269}, {"f": 1269}], [{"f": 1269}, {"f": 1269}, {"f": 1269}, {"f": 1269}, {"f": 1269}, {"f": 1269}, {"f": 1269}, {"f": 1269}, {"f": 1269}, {"f": 1269}, {"f": 1269}, {"f": 1269}, {"f": 1269}, {"f": 1269}, {"f": 1269}, {"f": 1269}, {"f": 1269}, {"f": 1269}, {"f": 1269}, {"f": 1269}, {"f": 1269}, {"f": 1269}, {"f": 1269}, {"f": 1269}, {"f": 1269}, {"f": 1269}, {"f": 1269}, {"f": 1269}, {"f": 1269}, {"f": 1269}, {"f": 1269}, {"f": 1269}, {"f": 1269}, {"f": 1269}, {"f": 1269}, {"f": 1269}, {"f": 1269}, {"f": 1269}, {"f": 1269}, {"f": 1269}, {"f": 1269}, {"f": 1269}, {"f": 1269}, {"f": 1269}, {"f": 1269}, {"f": 1269}, {"f": 1269}, {"f": 1269}, {"f": 1269}, {"f": 1269}, {"f": 1269}, {"f": 1269}, {"f": 1269}, {"f": 1269}, {"f": 1269}, {"f": 1269}, {"f": 1269}, {"f": 1269}, {"f": 1269}, {"f": 1269}, {"f": 1269}, {"f": 1269}, {"f": 1269}, {"f": 1269}], [{"f": 1269}, {"f": 1269}, {"f": 1269}, {"f": 1269}, {"f": 1269}, {"f": 1269}, {"f": 1269}, {"f": 1269}, {"f": 1269}, {"f": 1269}, {"f": 1269}, {"f": 1269}, {"f": 1269}, {"f": 1269}, {"f": 1269}, {"f": 1269}, {"f": 1269}, {"f": 1269}, {"f": 1269}, {"f": 1269}, {"f": 1269}, {"f": 1269}, {"f": 1269}, {"f": 1269}, {"f": 1269}, {"f": 1269}, {"f": 1269}, {"f": 1269}, {"f": 1269}, {"f": 1269}, {"f": 1269}, {"f": 1269}, {"f": 1269}, {"f": 1269}, {"f": 1269}, {"f": 1269}, {"f": 1269}, {"f": 1269}, {"f": 1269}, {"f": 1269}, {"f": 1269}, {"f": 1269}, {"f": 1269}, {"f": 1269}, {"f": 1269}, {"f": 1269}, {"f": 1269}, {"f": 1269}, {"f": 1269}, {"f": 1269}, {"f": 1269}, {"f": 1269}, {"f": 1269}, {"f": 1269}, {"f": 1269}, {"f": 1269}, {"f": 1269}, {"f": 1269}, {"f": 1269}, {"f": 1269}, {"f": 1269}, {"f": 1269}, {"f": 1269}, {"f": 1269}], [{"f": 1269}, {"f": 1269}, {"f": 1269}, {"f": 1269}, {"f": 1269}, {"f": 1269}, {"f": 1269}, {"f": 1269}, {"f": 1269}, {"f": 1269}, {"f": 1269}, {"f": 1269}, {"f": 1269}, {"f": 1269}, {"f": 1269}, {"f": 1269}, {"f": 1269}, {"f": 1269}, {"f": 1269}, {"f": 1269}, {"f": 1269}, {"f": 1269}, {"f": 1269}, {"f": 1269}, {"f": 1269}, {"f": 1269}, {"f": 1269}, {"f": 1269}, {"f": 1269}, {"f": 1269}, {"f": 1269}, {"f": 1269}, {"f": 1269}, {"f": 1269}, {"f": 1269}, {"f": 1269}, {"f": 1269}, {"f": 1269}, {"f": 1269}, {"f": 1269}, {"f": 1269}, {"f": 1269}, {"f": 1269}, {"f": 1269}, {"f": 1269}, {"f": 1269}, {"f": 1269}, {"f": 1269}, {"f": 1269}, {"f": 1269}, {"f": 1269}, {"f": 1269}, {"f": 1269}, {"f": 1269}, {"f": 1269}, {"f": 1269}, {"f": 1269}, {"f": 1269}, {"f": 1269}, {"f": 1269}, {"f": 1269}, {"f": 1269}, {"f": 1269}, {"f": 1269}], [{"f": 1269}, {"f": 1269}, {"f": 1269}, {"f": 1269}, {"f": 1269}, {"f": 1269}, {"f": 1269}, {"f": 1269}, {"f": 1269}, {"f": 1269}, {"f": 1269}, {"f": 1269}, {"f": 1269}, {"f": 1269}, {"f": 1269}, {"f": 1269}, {"f": 1269}, {"f": 1269}, {"f": 1269}, {"f": 1269}, {"f": 1269}, {"f": 1269}, {"f": 1269}, {"f": 1269}, {"f": 1269}, {"f": 1269}, {"f": 1269}, {"f": 1269}, {"f": 1269}, {"f": 1269}, {"f": 1269}, {"f": 1269}, {"f": 1269}, {"f": 1269}, {"f": 1269}, {"f": 1269}, {"f": 1269}, {"f": 1269}, {"f": 1269}, {"f": 1269}, {"f": 1269}, {"f": 1269}, {"f": 1269}, {"f": 1269}, {"f": 1269}, {"f": 1269}, {"f": 1269}, {"f": 1269}, {"f": 1269}, {"f": 1269}, {"f": 1269}, {"f": 1269}, {"f": 1269}, {"f": 1269}, {"f": 1269}, {"f": 1269}, {"f": 1269}, {"f": 1269}, {"f": 1269}, {"f": 1269}, {"f": 1269}, {"f": 1269}, {"f": 1269}, {"f": 1269}], [{"f": 1269}, {"f": 1269}, {"f": 1269}, {"f": 1269}, {"f": 1269}, {"f": 1269}, {"f": 1269}, {"f": 1269}, {"f": 1269}, {"f": 1269}, {"f": 1269}, {"f": 1269}, {"f": 1269}, {"f": 1269}, {"f": 1269}, {"f": 1269}, {"f": 1269}, {"f": 1269}, {"f": 1269}, {"f": 1269}, {"f": 1269}, {"f": 1269}, {"f": 1269}, {"f": 1269}, {"f": 1269}, {"f": 1269}, {"f": 1269}, {"f": 1269}, {"f": 1269}, {"f": 1269}, {"f": 1269}, {"f": 1269}, {"f": 1269}, {"f": 1269}, {"f": 1269}, {"f": 1269}, {"f": 1269}, {"f": 1269}, {"f": 1269}, {"f": 1269}, {"f": 1269}, {"f": 1269}, {"f": 1269}, {"f": 1269}, {"f": 1269}, {"f": 1269}, {"f": 1269}, {"f": 1269}, {"f": 1269}, {"f": 1269}, {"f": 1269}, {"f": 1269}, {"f": 1269}, {"f": 1269}, {"f": 1269}, {"f": 1269}, {"f": 1269}, {"f": 1269}, {"f": 1269}, {"f": 1269}, {"f": 1269}, {"f": 1269}, {"f": 1269}, {"f": 1269}], [{"f": 1269}, {"f": 1269}, {"f": 1269}, {"f": 1269}, {"f": 1269}, {"f": 1269}, {"f": 1269}, {"f": 1269}, {"f": 1269}, {"f": 1269}, {"f": 1269}, {"f": 1269}, {"f": 1269}, {"f": 1269}, {"f": 1269}, {"f": 1269}, {"f": 1269}, {"f": 1269}, {"f": 1269}, {"f": 1269}, {"f": 1269}, {"f": 1269}, {"f": 1269}, {"f": 1269}, {"f": 1269}, {"f": 1269}, {"f": 1269}, {"f": 1269}, {"f": 1269}, {"f": 1269}, {"f": 1269}, {"f": 1269}, {"f": 1269}, {"f": 1269}, {"f": 1269}, {"f": 1269}, {"f": 1269}, {"f": 1269}, {"f": 1269}, {"f": 1269}, {"f": 1269}, {"f": 1269}, {"f": 1269}, {"f": 1269}, {"f": 1269}, {"f": 1269}, {"f": 1269}, {"f": 1269}, {"f": 1269}, {"f": 1269}, {"f": 1269}, {"f": 1269}, {"f": 1269}, {"f": 1269}, {"f": 1269}, {"f": 1269}, {"f": 1269}, {"f": 1269}, {"f": 1269}, {"f": 1269}, {"f": 1269}, {"f": 1269}, {"f": 1269}, {"f": 1269}], [{"f": 1269}, {"f": 1269}, {"f": 1269}, {"f": 1269}, {"f": 1269}, {"f": 1269}, {"f": 1269}, {"f": 1269}, {"f": 1269}, {"f": 1269}, {"f": 1269}, {"f": 1269}, {"f": 1269}, {"f": 1269}, {"f": 1269}, {"f": 1269}, {"f": 1269}, {"f": 1269}, {"f": 1269}, {"f": 1269}, {"f": 1269}, {"f": 1269}, {"f": 1269}, {"f": 1269}, {"f": 1269}, {"f": 1269}, {"f": 1269}, {"f": 1269}, {"f": 1269}, {"f": 1269}, {"f": 1269}, {"f": 1269}, {"f": 1269}, {"f": 1269}, {"f": 1269}, {"f": 1269}, {"f": 1269}, {"f": 1269}, {"f": 1269}, {"f": 1269}, {"f": 1269}, {"f": 1269}, {"f": 1269}, {"f": 1269}, {"f": 1269}, {"f": 1269}, {"f": 1269}, {"f": 1269}, {"f": 1269}, {"f": 1269}, {"f": 1269}, {"f": 1269}, {"f": 1269}, {"f": 1269}, {"f": 1269}, {"f": 1269}, {"f": 1269}, {"f": 1269}, {"f": 1269}, {"f": 1269}, {"f": 1269}, {"f": 1269}, {"f": 1269}, {"f": 1269}], [{"f": 1269}, {"f": 1269}, {"f": 1269}, {"f": 1269}, {"f": 1269}, {"f": 1269}, {"f": 1269}, {"f": 1269}, {"f": 1269}, {"f": 1269}, {"f": 1269}, {"f": 1269}, {"f": 1269}, {"f": 1269}, {"f": 1269}, {"f": 1269}, {"f": 1269}, {"f": 1269}, {"f": 1269}, {"f": 1269}, {"f": 1269}, {"f": 1269}, {"f": 1269}, {"f": 1269}, {"f": 1269}, {"f": 1269}, {"f": 1269}, {"f": 1269}, {"f": 1269}, {"f": 1269}, {"f": 1269}, {"f": 1269}, {"f": 1269}, {"f": 1269}, {"f": 1269}, {"f": 1269}, {"f": 1269}, {"f": 1269}, {"f": 1269}, {"f": 1269}, {"f": 1269}, {"f": 1269}, {"f": 1269}, {"f": 1269}, {"f": 1269}, {"f": 1269}, {"f": 1269}, {"f": 1269}, {"f": 1269}, {"f": 1269}, {"f": 1269}, {"f": 1269}, {"f": 1269}, {"f": 1269}, {"f": 1269}, {"f": 1269}, {"f": 1269}, {"f": 1269}, {"f": 1269}, {"f": 1269}, {"f": 1269}, {"f": 1269}, {"f": 1269}, {"f": 1269}], [{"f": 1269}, {"f": 1269}, {"f": 1269}, {"f": 1269}, {"f": 1269}, {"f": 1269}, {"f": 1269}, {"f": 1269}, {"f": 1269}, {"f": 1269}, {"f": 1269}, {"f": 1269}, {"f": 1269}, {"f": 1269}, {"f": 1269}, {"f": 1269}, {"f": 1269}, {"f": 1269}, {"f": 1269}, {"f": 1269}, {"f": 1269}, {"f": 1269}, {"f": 1269}, {"f": 1269}, {"f": 1269}, {"f": 1269}, {"f": 1269}, {"f": 1269}, {"f": 1269}, {"f": 1269}, {"f": 1269}, {"f": 1269}, {"f": 1269}, {"f": 1269}, {"f": 1269}, {"f": 1269}, {"f": 1269}, {"f": 1269}, {"f": 1269}, {"f": 1269}, {"f": 1269}, {"f": 1269}, {"f": 1269}, {"f": 1269}, {"f": 1269}, {"f": 1269}, {"f": 1269}, {"f": 1269}, {"f": 1269}, {"f": 1269}, {"f": 1269}, {"f": 1269}, {"f": 1269}, {"f": 1269}, {"f": 1269}, {"f": 1269}, {"f": 1269}, {"f": 1269}, {"f": 1269}, {"f": 1269}, {"f": 1269}, {"f": 1269}, {"f": 1269}, {"f": 1269}], [{"f": 1269}, {"f": 1269}, {"f": 1269}, {"f": 1269}, {"f": 1269}, {"f": 1269}, {"f": 1269}, {"f": 1269}, {"f": 1269}, {"f": 1269}, {"f": 1269}, {"f": 1269}, {"f": 1269}, {"f": 1269}, {"f": 1269}, {"f": 1269}, {"f": 1269}, {"f": 1269}, {"f": 1269}, {"f": 1269}, {"f": 1269}, {"f": 1269}, {"f": 1269}, {"f": 1269}, {"f": 1269}, {"f": 1269}, {"f": 1269}, {"f": 1269}, {"f": 1269}, {"f": 1269}, {"f": 1269}, {"f": 1269}, {"f": 1269}, {"f": 1269}, {"f": 1269}, {"f": 1269}, {"f": 1269}, {"f": 1269}, {"f": 1269}, {"f": 1269}, {"f": 1269}, {"f": 1269}, {"f": 1269}, {"f": 1269}, {"f": 1269}, {"f": 1269}, {"f": 1269}, {"f": 1269}, {"f": 1269}, {"f": 1269}, {"f": 1269}, {"f": 1269}, {"f": 1269}, {"f": 1269}, {"f": 1269}, {"f": 1269}, {"f": 1269}, {"f": 1269}, {"f": 1269}, {"f": 1269}, {"f": 1269}, {"f": 1269}, {"f": 1269}, {"f": 1269}], [{"f": 1269}, {"f": 1269}, {"f": 1269}, {"f": 1269}, {"f": 1269}, {"f": 1269}, {"f": 1269}, {"f": 1269}, {"f": 1269}, {"f": 1269}, {"f": 1269}, {"f": 1269}, {"f": 1269}, {"f": 1269}, {"f": 1269}, {"f": 1269}, {"f": 1269}, {"f": 1269}, {"f": 1269}, {"f": 1269}, {"f": 1269}, {"f": 1269}, {"f": 1269}, {"f": 1269}, {"f": 1269}, {"f": 1269}, {"f": 1269}, {"f": 1269}, {"f": 1269}, {"f": 1269}, {"f": 1269}, {"f": 1269}, {"f": 1269}, {"f": 1269}, {"f": 1269}, {"f": 1269}, {"f": 1269}, {"f": 1269}, {"f": 1269}, {"f": 1269}, {"f": 1269}, {"f": 1269}, {"f": 1269}, {"f": 1269}, {"f": 1269}, {"f": 1269}, {"f": 1269}, {"f": 1269}, {"f": 1269}, {"f": 1269}, {"f": 1269}, {"f": 1269}, {"f": 1269}, {"f": 1269}, {"f": 1269}, {"f": 1269}, {"f": 1269}, {"f": 1269}, {"f": 1269}, {"f": 1269}, {"f": 1269}, {"f": 1269}, {"f": 1269}, {"f": 1269}], [{"f": 1269}, {"f": 1269}, {"f": 1269}, {"f": 1269}, {"f": 1269}, {"f": 1269}, {"f": 1269}, {"f": 1269}, {"f": 1269}, {"f": 1269}, {"f": 1269}, {"f": 1269}, {"f": 1269}, {"f": 1269}, {"f": 1269}, {"f": 1269}, {"f": 1269}, {"f": 1269}, {"f": 1269}, {"f": 1269}, {"f": 1269}, {"f": 1269}, {"f": 1269}, {"f": 1269}, {"f": 1269}, {"f": 1269}, {"f": 1269}, {"f": 1269}, {"f": 1269}, {"f": 1269}, {"f": 1269}, {"f": 1269}, {"f": 1269}, {"f": 1269}, {"f": 1269}, {"f": 1269}, {"f": 1269}, {"f": 1269}, {"f": 1269}, {"f": 1269}, {"f": 1269}, {"f": 1269}, {"f": 1269}, {"f": 1269}, {"f": 1269}, {"f": 1269}, {"f": 1269}, {"f": 1269}, {"f": 1269}, {"f": 1269}, {"f": 1269}, {"f": 1269}, {"f": 1269}, {"f": 1269}, {"f": 1269}, {"f": 1269}, {"f": 1269}, {"f": 1269}, {"f": 1269}, {"f": 1269}, {"f": 1269}, {"f": 1269}, {"f": 1269}, {"f": 1269}], [{"f": 1269}, {"f": 1269}, {"f": 1269}, {"f": 1269}, {"f": 1269}, {"f": 1269}, {"f": 1269}, {"f": 1269}, {"f": 1269}, {"f": 1269}, {"f": 1269}, {"f": 1269}, {"f": 1269}, {"f": 1269}, {"f": 1269}, {"f": 1269}, {"f": 1269}, {"f": 1269}, {"f": 1269}, {"f": 1269}, {"f": 1269}, {"f": 1269}, {"f": 1269}, {"f": 1269}, {"f": 1269}, {"f": 1269}, {"f": 1269}, {"f": 1269}, {"f": 1269}, {"f": 1269}, {"f": 1269}, {"f": 1269}, {"f": 1269}, {"f": 1269}, {"f": 1269}, {"f": 1269}, {"f": 1269}, {"f": 1269}, {"f": 1269}, {"f": 1269}, {"f": 1269}, {"f": 1269}, {"f": 1269}, {"f": 1269}, {"f": 1269}, {"f": 1269}, {"f": 1269}, {"f": 1269}, {"f": 1269}, {"f": 1269}, {"f": 1269}, {"f": 1269}, {"f": 1269}, {"f": 1269}, {"f": 1269}, {"f": 1269}, {"f": 1269}, {"f": 1269}, {"f": 1269}, {"f": 1269}, {"f": 1269}, {"f": 1269}, {"f": 1269}, {"f": 1269}], [{"f": 1269}, {"f": 1269}, {"f": 1269}, {"f": 1269}, {"f": 1269}, {"f": 1269}, {"f": 1269}, {"f": 1269}, {"f": 1269}, {"f": 1269}, {"f": 1269}, {"f": 1269}, {"f": 1269}, {"f": 1269}, {"f": 1269}, {"f": 1269}, {"f": 1269}, {"f": 1269}, {"f": 1269}, {"f": 1269}, {"f": 1269}, {"f": 1269}, {"f": 1269}, {"f": 1269}, {"f": 1269}, {"f": 1269}, {"f": 1269}, {"f": 1269}, {"f": 1269}, {"f": 1269}, {"f": 1269}, {"f": 1269}, {"f": 1269}, {"f": 1269}, {"f": 1269}, {"f": 1269}, {"f": 1269}, {"f": 1269}, {"f": 1269}, {"f": 1269}, {"f": 1269}, {"f": 1269}, {"f": 1269}, {"f": 1269}, {"f": 1269}, {"f": 1269}, {"f": 1269}, {"f": 1269}, {"f": 1269}, {"f": 1269}, {"f": 1269}, {"f": 1269}, {"f": 1269}, {"f": 1269}, {"f": 1269}, {"f": 1269}, {"f": 1269}, {"f": 1269}, {"f": 1269}, {"f": 1269}, {"f": 1269}, {"f": 1269}, {"f": 1269}, {"f": 1269}], [{"f": 1269}, {"f": 1269}, {"f": 1269}, {"f": 1269}, {"f": 1269}, {"f": 1269}, {"f": 1269}, {"f": 1269}, {"f": 1269}, {"f": 1269}, {"f": 1269}, {"f": 1269}, {"f": 1269}, {"f": 1269}, {"f": 1269}, {"f": 1269}, {"f": 1269}, {"f": 1269}, {"f": 1269}, {"f": 1269}, {"f": 1269}, {"f": 1269}, {"f": 1269}, {"f": 1269}, {"f": 1269}, {"f": 1269}, {"f": 1269}, {"f": 1269}, {"f": 1269}, {"f": 1269}, {"f": 1269}, {"f": 1269}, {"f": 1269}, {"f": 1269}, {"f": 1269}, {"f": 1269}, {"f": 1269}, {"f": 1269}, {"f": 1269}, {"f": 1269}, {"f": 1269}, {"f": 1269}, {"f": 1269}, {"f": 1269}, {"f": 1269}, {"f": 1269}, {"f": 1269}, {"f": 1269}, {"f": 1269}, {"f": 1269}, {"f": 1269}, {"f": 1269}, {"f": 1269}, {"f": 1269}, {"f": 1269}, {"f": 1269}, {"f": 1269}, {"f": 1269}, {"f": 1269}, {"f": 1269}, {"f": 1269}, {"f": 1269}, {"f": 1269}, {"f": 1269}], [{"f": 1269}, {"f": 1269}, {"f": 1269}, {"f": 1269}, {"f": 1269}, {"f": 1269}, {"f": 1269}, {"f": 1269}, {"f": 1269}, {"f": 1269}, {"f": 1269}, {"f": 1269}, {"f": 1269}, {"f": 1269}, {"f": 1269}, {"f": 1269}, {"f": 1269}, {"f": 1269}, {"f": 1269}, {"f": 1269}, {"f": 1269}, {"f": 1269}, {"f": 1269}, {"f": 1269}, {"f": 1269}, {"f": 1269}, {"f": 1269}, {"f": 1269}, {"f": 1269}, {"f": 1269}, {"f": 1269}, {"f": 1269}, {"f": 1269}, {"f": 1269}, {"f": 1269}, {"f": 1269}, {"f": 1269}, {"f": 1269}, {"f": 1269}, {"f": 1269}, {"f": 1269}, {"f": 1269}, {"f": 1269}, {"f": 1269}, {"f": 1269}, {"f": 1269}, {"f": 1269}, {"f": 1269}, {"f": 1269}, {"f": 1269}, {"f": 1269}, {"f": 1269}, {"f": 1269}, {"f": 1269}, {"f": 1269}, {"f": 1269}, {"f": 1269}, {"f": 1269}, {"f": 1269}, {"f": 1269}, {"f": 1269}, {"f": 1269}, {"f": 1269}, {"f": 1269}], [{"f": 1269}, {"f": 1269}, {"f": 1269}, {"f": 1269}, {"f": 1269}, {"f": 1269}, {"f": 1269}, {"f": 1269}, {"f": 1269}, {"f": 1269}, {"f": 1269}, {"f": 1269}, {"f": 1269}, {"f": 1269}, {"f": 1269}, {"f": 1269}, {"f": 1269}, {"f": 1269}, {"f": 1269}, {"f": 1269}, {"f": 1269}, {"f": 1269}, {"f": 1269}, {"f": 1269}, {"f": 1269}, {"f": 1269}, {"f": 1269}, {"f": 1269}, {"f": 1269}, {"f": 1269}, {"f": 1269}, {"f": 1269}, {"f": 1269}, {"f": 1269}, {"f": 1269}, {"f": 1269}, {"f": 1269}, {"f": 1269}, {"f": 1269}, {"f": 1269}, {"f": 1269}, {"f": 1269}, {"f": 1269}, {"f": 1269}, {"f": 1269}, {"f": 1269}, {"f": 1269}, {"f": 1269}, {"f": 1269}, {"f": 1269}, {"f": 1269}, {"f": 1269}, {"f": 1269}, {"f": 1269}, {"f": 1269}, {"f": 1269}, {"f": 1269}, {"f": 1269}, {"f": 1269}, {"f": 1269}, {"f": 1269}, {"f": 1269}, {"f": 1269}, {"f": 1269}], [{"f": 1269}, {"f": 1269}, {"f": 1269}, {"f": 1269}, {"f": 1269}, {"f": 1269}, {"f": 1269}, {"f": 1269}, {"f": 1269}, {"f": 1269}, {"f": 1269}, {"f": 1269}, {"f": 1269}, {"f": 1269}, {"f": 1269}, {"f": 1269}, {"f": 1269}, {"f": 1269}, {"f": 1269}, {"f": 1269}, {"f": 1269}, {"f": 1269}, {"f": 1269}, {"f": 1269}, {"f": 1269}, {"f": 1269}, {"f": 1269}, {"f": 1269}, {"f": 1269}, {"f": 1269}, {"f": 1269}, {"f": 1269}, {"f": 1269}, {"f": 1269}, {"f": 1269}, {"f": 1269}, {"f": 1269}, {"f": 1269}, {"f": 1269}, {"f": 1269}, {"f": 1269}, {"f": 1269}, {"f": 1269}, {"f": 1269}, {"f": 1269}, {"f": 1269}, {"f": 1269}, {"f": 1269}, {"f": 1269}, {"f": 1269}, {"f": 1269}, {"f": 1269}, {"f": 1269}, {"f": 1269}, {"f": 1269}, {"f": 1269}, {"f": 1269}, {"f": 1269}, {"f": 1269}, {"f": 1269}, {"f": 1269}, {"f": 1269}, {"f": 1269}, {"f": 1269}], [{"f": 1269}, {"f": 1269}, {"f": 1269}, {"f": 1269}, {"f": 1269}, {"f": 1269}, {"f": 1269}, {"f": 1269}, {"f": 1269}, {"f": 1269}, {"f": 1269}, {"f": 1269}, {"f": 1269}, {"f": 1269}, {"f": 1269}, {"f": 1269}, {"f": 1269}, {"f": 1269}, {"f": 1269}, {"f": 1269}, {"f": 1269}, {"f": 1269}, {"f": 1269}, {"f": 1269}, {"f": 1269}, {"f": 1269}, {"f": 1269}, {"f": 1269}, {"f": 1269}, {"f": 1269}, {"f": 1269}, {"f": 1269}, {"f": 1269}, {"f": 1269}, {"f": 1269}, {"f": 1269}, {"f": 1269}, {"f": 1269}, {"f": 1269}, {"f": 1269}, {"f": 1269}, {"f": 1269}, {"f": 1269}, {"f": 1269}, {"f": 1269}, {"f": 1269}, {"f": 1269}, {"f": 1269}, {"f": 1269}, {"f": 1269}, {"f": 1269}, {"f": 1269}, {"f": 1269}, {"f": 1269}, {"f": 1269}, {"f": 1269}, {"f": 1269}, {"f": 1269}, {"f": 1269}, {"f": 1269}, {"f": 1269}, {"f": 1269}, {"f": 1269}, {"f": 1269}], [{"f": 1269}, {"f": 1269}, {"f": 1269}, {"f": 1269}, {"f": 1269}, {"f": 1269}, {"f": 1269}, {"f": 1269}, {"f": 1269}, {"f": 1269}, {"f": 1269}, {"f": 1269}, {"f": 1269}, {"f": 1269}, {"f": 1269}, {"f": 1269}, {"f": 1269}, {"f": 1269}, {"f": 1269}, {"f": 1269}, {"f": 1269}, {"f": 1269}, {"f": 1269}, {"f": 1269}, {"f": 1269}, {"f": 1269}, {"f": 1269}, {"f": 1269}, {"f": 1269}, {"f": 1269}, {"f": 1269}, {"f": 1269}, {"f": 1269}, {"f": 1269}, {"f": 1269}, {"f": 1269}, {"f": 1269}, {"f": 1269}, {"f": 1269}, {"f": 1269}, {"f": 1269}, {"f": 1269}, {"f": 1269}, {"f": 1269}, {"f": 1269}, {"f": 1269}, {"f": 1269}, {"f": 1269}, {"f": 1269}, {"f": 1269}, {"f": 1269}, {"f": 1269}, {"f": 1269}, {"f": 1269}, {"f": 1269}, {"f": 1269}, {"f": 1269}, {"f": 1269}, {"f": 1269}, {"f": 1269}, {"f": 1269}, {"f": 1269}, {"f": 1269}, {"f": 1269}], [{"f": 1269}, {"f": 1269}, {"f": 1269}, {"f": 1269}, {"f": 1269}, {"f": 1269}, {"f": 1269}, {"f": 1269}, {"f": 1269}, {"f": 1269}, {"f": 1269}, {"f": 1269}, {"f": 1269}, {"f": 1269}, {"f": 1269}, {"f": 1269}, {"f": 1269}, {"f": 1269}, {"f": 1269}, {"f": 1269}, {"f": 1269}, {"f": 1269}, {"f": 1269}, {"f": 1269}, {"f": 1269}, {"f": 1269}, {"f": 1269}, {"f": 1269}, {"f": 1269}, {"f": 1269}, {"f": 1269}, {"f": 1269}, {"f": 1269}, {"f": 1269}, {"f": 1269}, {"f": 1269}, {"f": 1269}, {"f": 1269}, {"f": 1269}, {"f": 1269}, {"f": 1269}, {"f": 1269}, {"f": 1269}, {"f": 1269}, {"f": 1269}, {"f": 1269}, {"f": 1269}, {"f": 1269}, {"f": 1269}, {"f": 1269}, {"f": 1269}, {"f": 1269}, {"f": 1269}, {"f": 1269}, {"f": 1269}, {"f": 1269}, {"f": 1269}, {"f": 1269}, {"f": 1269}, {"f": 1269}, {"f": 1269}, {"f": 1269}, {"f": 1269}, {"f": 1269}], [{"f": 1269}, {"f": 1269}, {"f": 1269}, {"f": 1269}, {"f": 1269}, {"f": 1269}, {"f": 1269}, {"f": 1269}, {"f": 1269}, {"f": 1269}, {"f": 1269}, {"f": 1269}, {"f": 1269}, {"f": 1269}, {"f": 1269}, {"f": 1269}, {"f": 1269}, {"f": 1269}, {"f": 1269}, {"f": 1269}, {"f": 1269}, {"f": 1269}, {"f": 1269}, {"f": 1269}, {"f": 1269}, {"f": 1269}, {"f": 1269}, {"f": 1269}, {"f": 1269}, {"f": 1269}, {"f": 1269}, {"f": 1269}, {"f": 1269}, {"f": 1269}, {"f": 1269}, {"f": 1269}, {"f": 1269}, {"f": 1269}, {"f": 1269}, {"f": 1269}, {"f": 1269}, {"f": 1269}, {"f": 1269}, {"f": 1269}, {"f": 1269}, {"f": 1269}, {"f": 1269}, {"f": 1269}, {"f": 1269}, {"f": 1269}, {"f": 1269}, {"f": 1269}, {"f": 1269}, {"f": 1269}, {"f": 1269}, {"f": 1269}, {"f": 1269}, {"f": 1269}, {"f": 1269}, {"f": 1269}, {"f": 1269}, {"f": 1269}, {"f": 1269}, {"f": 1269}], [{"f": 1269}, {"f": 1269}, {"f": 1269}, {"f": 1269}, {"f": 1269}, {"f": 1269}, {"f": 1269}, {"f": 1269}, {"f": 1269}, {"f": 1269}, {"f": 1269}, {"f": 1269}, {"f": 1269}, {"f": 1269}, {"f": 1269}, {"f": 1269}, {"f": 1269}, {"f": 1269}, {"f": 1269}, {"f": 1269}, {"f": 1269}, {"f": 1269}, {"f": 1269}, {"f": 1269}, {"f": 1269}, {"f": 1269}, {"f": 1269}, {"f": 1269}, {"f": 1269}, {"f": 1269}, {"f": 1269}, {"f": 1269}, {"f": 1269}, {"f": 1269}, {"f": 1269}, {"f": 1269}, {"f": 1269}, {"f": 1269}, {"f": 1269}, {"f": 1269}, {"f": 1269}, {"f": 1269}, {"f": 1269}, {"f": 1269}, {"f": 1269}, {"f": 1269}, {"f": 1269}, {"f": 1269}, {"f": 1269}, {"f": 1269}, {"f": 1269}, {"f": 1269}, {"f": 1269}, {"f": 1269}, {"f": 1269}, {"f": 1269}, {"f": 1269}, {"f": 1269}, {"f": 1269}, {"f": 1269}, {"f": 1269}, {"f": 1269}, {"f": 1269}, {"f": 1269}]]